{
  "version": "2.0",
  "model": "ensemble",
  "ensemble_models": [
    "A",
    "B",
    "C",
    "D",
    "E",
    "F",
    "G"
  ],
  "character": "莉莉娅",
  "source_image": "莉莉娅_全身.png",
  "image_width": 1024,
  "image_height": 1024,
  "ensemble_avg_score": 0.9924537504420561,
  "per_model_avg": {
    "A": 0.7940049171447754,
    "B": 0.8209099769592285,
    "C": 0.9879117012023926,
    "E": 0.7945372462272644,
    "F": 0.8633263111114502,
    "G": 0.9881901741027832
  },
  "source_distribution": {
    "G": 5,
    "C": 4,
    "F": 8
  },
  "landmarks": [
    {
      "id": 0,
      "name": "nose",
      "x": 0.4343438073992729,
      "y": 0.22236102260649204,
      "score": 0.9986573457717896,
      "visibility": 0.9986573457717896,
      "source_model": "G"
    },
    {
      "id": 1,
      "name": "left_eye",
      "x": 0.455723088234663,
      "y": 0.2055630162358284,
      "score": 0.9992958307266235,
      "visibility": 0.9992958307266235,
      "source_model": "G"
    },
    {
      "id": 2,
      "name": "right_eye",
      "x": 0.4261664930317137,
      "y": 0.2046445760255058,
      "score": 0.999267041683197,
      "visibility": 0.999267041683197,
      "source_model": "C"
    },
    {
      "id": 3,
      "name": "left_ear",
      "x": 0.4801565520465374,
      "y": 0.2086171992123127,
      "score": 0.9943769574165344,
      "visibility": 0.9943769574165344,
      "source_model": "G"
    },
    {
      "id": 4,
      "name": "right_ear",
      "x": 0.4186416197982099,
      "y": 0.21216944900030899,
      "score": 0.9952830672264099,
      "visibility": 0.9952830672264099,
      "source_model": "C"
    },
    {
      "id": 5,
      "name": "left_shoulder",
      "x": 0.49196600914001465,
      "y": 0.28243765234947205,
      "score": 0.9992226362228394,
      "visibility": 0.9992226362228394,
      "source_model": "F"
    },
    {
      "id": 6,
      "name": "right_shoulder",
      "x": 0.40827512741088867,
      "y": 0.27674680948257446,
      "score": 0.9930819869041443,
      "visibility": 0.9930819869041443,
      "source_model": "F"
    },
    {
      "id": 7,
      "name": "left_elbow",
      "x": 0.541706919670105,
      "y": 0.3918256461620331,
      "score": 0.9997379183769226,
      "visibility": 0.9997379183769226,
      "source_model": "F"
    },
    {
      "id": 8,
      "name": "right_elbow",
      "x": 0.3503537755459547,
      "y": 0.3781243544071913,
      "score": 0.969222903251648,
      "visibility": 0.969222903251648,
      "source_model": "G"
    },
    {
      "id": 9,
      "name": "left_wrist",
      "x": 0.4740481860935688,
      "y": 0.4682227522134781,
      "score": 0.9980233907699585,
      "visibility": 0.9980233907699585,
      "source_model": "G"
    },
    {
      "id": 10,
      "name": "right_wrist",
      "x": 0.39155207615759635,
      "y": 0.4755400031184158,
      "score": 0.9309371709823608,
      "visibility": 0.9309371709823608,
      "source_model": "C"
    },
    {
      "id": 11,
      "name": "left_hip",
      "x": 0.4660032391548157,
      "y": 0.4908086657524109,
      "score": 0.999502420425415,
      "visibility": 0.999502420425415,
      "source_model": "F"
    },
    {
      "id": 12,
      "name": "right_hip",
      "x": 0.3976249098777771,
      "y": 0.4880445897579193,
      "score": 0.997552216053009,
      "visibility": 0.997552216053009,
      "source_model": "F"
    },
    {
      "id": 13,
      "name": "left_knee",
      "x": 0.49274128675460815,
      "y": 0.6796408891677856,
      "score": 0.9998142123222351,
      "visibility": 0.9998142123222351,
      "source_model": "F"
    },
    {
      "id": 14,
      "name": "right_knee",
      "x": 0.4075213372707367,
      "y": 0.6804836392402649,
      "score": 0.9991868138313293,
      "visibility": 0.9991868138313293,
      "source_model": "F"
    },
    {
      "id": 15,
      "name": "left_ankle",
      "x": 0.5198951363563538,
      "y": 0.8699723482131958,
      "score": 0.9996412992477417,
      "visibility": 0.9996412992477417,
      "source_model": "F"
    },
    {
      "id": 16,
      "name": "right_ankle",
      "x": 0.40509684797790313,
      "y": 0.8698433469980955,
      "score": 0.9989105463027954,
      "visibility": 0.9989105463027954,
      "source_model": "C"
    }
  ]
}