{
  "version": "2.0",
  "model": "ensemble",
  "ensemble_models": [
    "A",
    "B",
    "C",
    "D",
    "E",
    "F",
    "G"
  ],
  "character": "苏苏洛",
  "source_image": "苏苏洛_全身.png",
  "image_width": 1024,
  "image_height": 1024,
  "ensemble_avg_score": 0.9974650039392359,
  "per_model_avg": {
    "A": 0.7973147034645081,
    "B": 0.8115789890289307,
    "C": 0.990914523601532,
    "E": 0.8605324029922485,
    "F": 0.9501357078552246,
    "G": 0.9915468692779541
  },
  "source_distribution": {
    "G": 4,
    "C": 3,
    "F": 10
  },
  "landmarks": [
    {
      "id": 0,
      "name": "nose",
      "x": 0.49329512317975366,
      "y": 0.19632250567277265,
      "score": 0.9983572363853455,
      "visibility": 0.9983572363853455,
      "source_model": "G"
    },
    {
      "id": 1,
      "name": "left_eye",
      "x": 0.5138788372278214,
      "y": 0.17573879162470507,
      "score": 0.9994600415229797,
      "visibility": 0.9994600415229797,
      "source_model": "G"
    },
    {
      "id": 2,
      "name": "right_eye",
      "x": 0.46321123341719306,
      "y": 0.18207224210103345,
      "score": 0.9996664524078369,
      "visibility": 0.9996664524078369,
      "source_model": "G"
    },
    {
      "id": 3,
      "name": "left_ear",
      "x": 0.5322928068538506,
      "y": 0.17790293119226885,
      "score": 0.9959403276443481,
      "visibility": 0.9959403276443481,
      "source_model": "C"
    },
    {
      "id": 4,
      "name": "right_ear",
      "x": 0.4387184453921186,
      "y": 0.18741896826152993,
      "score": 0.9952072501182556,
      "visibility": 0.9952072501182556,
      "source_model": "C"
    },
    {
      "id": 5,
      "name": "left_shoulder",
      "x": 0.5618968605995178,
      "y": 0.23986272513866425,
      "score": 0.999126136302948,
      "visibility": 0.999126136302948,
      "source_model": "F"
    },
    {
      "id": 6,
      "name": "right_shoulder",
      "x": 0.4200611710548401,
      "y": 0.259981632232666,
      "score": 0.9979202151298523,
      "visibility": 0.9979202151298523,
      "source_model": "F"
    },
    {
      "id": 7,
      "name": "left_elbow",
      "x": 0.6124156713485718,
      "y": 0.2990761399269104,
      "score": 0.999593198299408,
      "visibility": 0.999593198299408,
      "source_model": "F"
    },
    {
      "id": 8,
      "name": "right_elbow",
      "x": 0.3783792555332184,
      "y": 0.3647529184818268,
      "score": 0.990744948387146,
      "visibility": 0.990744948387146,
      "source_model": "F"
    },
    {
      "id": 9,
      "name": "left_wrist",
      "x": 0.7166445851325989,
      "y": 0.29749956727027893,
      "score": 0.999265730381012,
      "visibility": 0.999265730381012,
      "source_model": "F"
    },
    {
      "id": 10,
      "name": "right_wrist",
      "x": 0.3252473473548889,
      "y": 0.44500732421875,
      "score": 0.9895952343940735,
      "visibility": 0.9895952343940735,
      "source_model": "F"
    },
    {
      "id": 11,
      "name": "left_hip",
      "x": 0.5679234266281128,
      "y": 0.5027701258659363,
      "score": 0.9997996687889099,
      "visibility": 0.9997996687889099,
      "source_model": "F"
    },
    {
      "id": 12,
      "name": "right_hip",
      "x": 0.4714406132698059,
      "y": 0.5088011026382446,
      "score": 0.9996514320373535,
      "visibility": 0.9996514320373535,
      "source_model": "F"
    },
    {
      "id": 13,
      "name": "left_knee",
      "x": 0.5509162545204163,
      "y": 0.6899399757385254,
      "score": 0.9995793700218201,
      "visibility": 0.9995793700218201,
      "source_model": "F"
    },
    {
      "id": 14,
      "name": "right_knee",
      "x": 0.4433813691139221,
      "y": 0.6919642686843872,
      "score": 0.9991693496704102,
      "visibility": 0.9991693496704102,
      "source_model": "F"
    },
    {
      "id": 15,
      "name": "left_ankle",
      "x": 0.5322928068538506,
      "y": 0.8757456496047478,
      "score": 0.996907651424408,
      "visibility": 0.996907651424408,
      "source_model": "C"
    },
    {
      "id": 16,
      "name": "right_ankle",
      "x": 0.3998767286539078,
      "y": 0.8565847178300221,
      "score": 0.9969208240509033,
      "visibility": 0.9969208240509033,
      "source_model": "G"
    }
  ]
}