{
  "version": "2.0",
  "model": "ensemble",
  "ensemble_models": [
    "A",
    "B",
    "C",
    "D",
    "E",
    "F",
    "G"
  ],
  "character": "蓝毒",
  "source_image": "蓝毒_全身.png",
  "image_width": 1024,
  "image_height": 1024,
  "ensemble_avg_score": 0.995896528748905,
  "per_model_avg": {
    "A": 0.6768632531166077,
    "B": 0.7694355845451355,
    "C": 0.9841851592063904,
    "E": 0.7524052858352661,
    "F": 0.9148188233375549,
    "G": 0.9816794395446777
  },
  "source_distribution": {
    "C": 5,
    "F": 11,
    "G": 1
  },
  "landmarks": [
    {
      "id": 0,
      "name": "nose",
      "x": 0.4627782865944836,
      "y": 0.18079476136093342,
      "score": 0.9958827495574951,
      "visibility": 0.9958827495574951,
      "source_model": "C"
    },
    {
      "id": 1,
      "name": "left_eye",
      "x": 0.4935607289274534,
      "y": 0.15325257523606217,
      "score": 0.9979915618896484,
      "visibility": 0.9979915618896484,
      "source_model": "C"
    },
    {
      "id": 2,
      "name": "right_eye",
      "x": 0.44657700115607846,
      "y": 0.15973308961838484,
      "score": 0.9984744191169739,
      "visibility": 0.9984744191169739,
      "source_model": "C"
    },
    {
      "id": 3,
      "name": "left_ear",
      "x": 0.5389243281549878,
      "y": 0.17431424697861075,
      "score": 0.9838770031929016,
      "visibility": 0.9838770031929016,
      "source_model": "C"
    },
    {
      "id": 4,
      "name": "right_ear",
      "x": 0.43523610134919477,
      "y": 0.17269411838303006,
      "score": 0.9882458448410034,
      "visibility": 0.9882458448410034,
      "source_model": "C"
    },
    {
      "id": 5,
      "name": "left_shoulder",
      "x": 0.5472698211669922,
      "y": 0.24815614521503448,
      "score": 0.9997444748878479,
      "visibility": 0.9997444748878479,
      "source_model": "F"
    },
    {
      "id": 6,
      "name": "right_shoulder",
      "x": 0.4432554841041565,
      "y": 0.2709314525127411,
      "score": 0.9988811612129211,
      "visibility": 0.9988811612129211,
      "source_model": "F"
    },
    {
      "id": 7,
      "name": "left_elbow",
      "x": 0.44430011510849,
      "y": 0.2488528937101364,
      "score": 0.9991033673286438,
      "visibility": 0.9991033673286438,
      "source_model": "F"
    },
    {
      "id": 8,
      "name": "right_elbow",
      "x": 0.41166263818740845,
      "y": 0.3763425946235657,
      "score": 0.9881827235221863,
      "visibility": 0.9881827235221863,
      "source_model": "F"
    },
    {
      "id": 9,
      "name": "left_wrist",
      "x": 0.4098048806190491,
      "y": 0.19663052260875702,
      "score": 0.9960129261016846,
      "visibility": 0.9960129261016846,
      "source_model": "F"
    },
    {
      "id": 10,
      "name": "right_wrist",
      "x": 0.37250572443008423,
      "y": 0.4590379595756531,
      "score": 0.9901485443115234,
      "visibility": 0.9901485443115234,
      "source_model": "F"
    },
    {
      "id": 11,
      "name": "left_hip",
      "x": 0.5241327285766602,
      "y": 0.4718037247657776,
      "score": 0.9999675750732422,
      "visibility": 0.9999675750732422,
      "source_model": "F"
    },
    {
      "id": 12,
      "name": "right_hip",
      "x": 0.46581926941871643,
      "y": 0.4799613952636719,
      "score": 0.9999101161956787,
      "visibility": 0.9999101161956787,
      "source_model": "F"
    },
    {
      "id": 13,
      "name": "left_knee",
      "x": 0.4200916886329651,
      "y": 0.6503897309303284,
      "score": 0.9996683597564697,
      "visibility": 0.9996683597564697,
      "source_model": "F"
    },
    {
      "id": 14,
      "name": "right_knee",
      "x": 0.5283036231994629,
      "y": 0.6790731549263,
      "score": 0.9992774128913879,
      "visibility": 0.9992774128913879,
      "source_model": "F"
    },
    {
      "id": 15,
      "name": "left_ankle",
      "x": 0.5987589955329895,
      "y": 0.6680231094360352,
      "score": 0.9976840019226074,
      "visibility": 0.9976840019226074,
      "source_model": "F"
    },
    {
      "id": 16,
      "name": "right_ankle",
      "x": 0.5822949937234321,
      "y": 0.8704954907298088,
      "score": 0.9971887469291687,
      "visibility": 0.9971887469291687,
      "source_model": "G"
    }
  ]
}