{
  "MapName":"宿舍5区",
  "PathEdge":{
    "0":{"舍管房":1,"外走廊":1},
    "舍管房":{"0":1},
    "外走廊":{"0":1,"内走廊":1,"501":1,"502":1,"503":1,"504":1,"505":1,"506":1,"512":1,"513":1},
    "内走廊":{"外走廊":1,"507":1,"508":1,"509":1,"510":1,"511":1},
    "501":{"外走廊":1},
    "502":{"外走廊":1},
    "503":{"外走廊":1},
    "504":{"外走廊":1},
    "505":{"外走廊":1},
    "506":{"外走廊":1},
    "507":{"内走廊":1},
    "508":{"内走廊":1},
    "509":{"内走廊":1},
    "510":{"内走廊":1},
    "511":{"内走廊":1},
    "512":{"外走廊":1},
    "513":{"外走廊":1}
  }
}