{
  "version": "2.0",
  "model": "ensemble",
  "ensemble_models": [
    "A",
    "B",
    "C",
    "D",
    "E",
    "F",
    "G"
  ],
  "character": "深海色",
  "source_image": "深海色_全身.png",
  "image_width": 1024,
  "image_height": 1024,
  "ensemble_avg_score": 0.9878647642977098,
  "per_model_avg": {
    "A": 0.7489211559295654,
    "B": 0.7177067995071411,
    "C": 0.9823359251022339,
    "E": 0.6725648045539856,
    "F": 0.9512190222740173,
    "G": 0.9840052127838135
  },
  "source_distribution": {
    "G": 5,
    "C": 4,
    "F": 8
  },
  "landmarks": [
    {
      "id": 0,
      "name": "nose",
      "x": 0.4918222390115261,
      "y": 0.17342296242713928,
      "score": 0.9975252747535706,
      "visibility": 0.9975252747535706,
      "source_model": "G"
    },
    {
      "id": 1,
      "name": "left_eye",
      "x": 0.5085683142145475,
      "y": 0.1576277781277895,
      "score": 0.9993195533752441,
      "visibility": 0.9993195533752441,
      "source_model": "C"
    },
    {
      "id": 2,
      "name": "right_eye",
      "x": 0.46489772138496244,
      "y": 0.15115806087851524,
      "score": 0.9996931552886963,
      "visibility": 0.9996931552886963,
      "source_model": "C"
    },
    {
      "id": 3,
      "name": "left_ear",
      "x": 0.5198903197629584,
      "y": 0.170567212626338,
      "score": 0.9961308240890503,
      "visibility": 0.9961308240890503,
      "source_model": "C"
    },
    {
      "id": 4,
      "name": "right_ear",
      "x": 0.4366270340979099,
      "y": 0.15718907862901688,
      "score": 0.996322512626648,
      "visibility": 0.996322512626648,
      "source_model": "G"
    },
    {
      "id": 5,
      "name": "left_shoulder",
      "x": 0.540913462638855,
      "y": 0.2666469216346741,
      "score": 0.9998868703842163,
      "visibility": 0.9998868703842163,
      "source_model": "F"
    },
    {
      "id": 6,
      "name": "right_shoulder",
      "x": 0.4069492220878601,
      "y": 0.25139495730400085,
      "score": 0.9998846054077148,
      "visibility": 0.9998846054077148,
      "source_model": "F"
    },
    {
      "id": 7,
      "name": "left_elbow",
      "x": 0.5713682696223259,
      "y": 0.306540809571743,
      "score": 0.9524493217468262,
      "visibility": 0.9524493217468262,
      "source_model": "G"
    },
    {
      "id": 8,
      "name": "right_elbow",
      "x": 0.38467860594391823,
      "y": 0.3584892377257347,
      "score": 0.9573240876197815,
      "visibility": 0.9573240876197815,
      "source_model": "G"
    },
    {
      "id": 9,
      "name": "left_wrist",
      "x": 0.599144358601835,
      "y": 0.22717723855748773,
      "score": 0.99346923828125,
      "visibility": 0.99346923828125,
      "source_model": "C"
    },
    {
      "id": 10,
      "name": "right_wrist",
      "x": 0.39766571298241615,
      "y": 0.35199568420648575,
      "score": 0.914999783039093,
      "visibility": 0.914999783039093,
      "source_model": "G"
    },
    {
      "id": 11,
      "name": "left_hip",
      "x": 0.5501257181167603,
      "y": 0.4841291010379791,
      "score": 0.9994609951972961,
      "visibility": 0.9994609951972961,
      "source_model": "F"
    },
    {
      "id": 12,
      "name": "right_hip",
      "x": 0.4763011038303375,
      "y": 0.48585739731788635,
      "score": 0.999647855758667,
      "visibility": 0.999647855758667,
      "source_model": "F"
    },
    {
      "id": 13,
      "name": "left_knee",
      "x": 0.5588685870170593,
      "y": 0.6595093607902527,
      "score": 0.9994614720344543,
      "visibility": 0.9994614720344543,
      "source_model": "F"
    },
    {
      "id": 14,
      "name": "right_knee",
      "x": 0.5407724380493164,
      "y": 0.6520310640335083,
      "score": 0.9998874664306641,
      "visibility": 0.9998874664306641,
      "source_model": "F"
    },
    {
      "id": 15,
      "name": "left_ankle",
      "x": 0.5634602308273315,
      "y": 0.8646500706672668,
      "score": 0.9926993250846863,
      "visibility": 0.9926993250846863,
      "source_model": "F"
    },
    {
      "id": 16,
      "name": "right_ankle",
      "x": 0.6042250394821167,
      "y": 0.8827000856399536,
      "score": 0.9955386519432068,
      "visibility": 0.9955386519432068,
      "source_model": "F"
    }
  ]
}