{
  "version": "2.0",
  "model": "ensemble",
  "ensemble_models": [
    "A",
    "B",
    "C",
    "D",
    "E",
    "F",
    "G"
  ],
  "character": "杜遥夜",
  "source_image": "杜遥夜_全身.png",
  "image_width": 1024,
  "image_height": 1024,
  "ensemble_avg_score": 0.9909996425404268,
  "per_model_avg": {
    "A": 0.6815719604492188,
    "B": 0.7389604449272156,
    "C": 0.9801550507545471,
    "E": 0.7411000728607178,
    "F": 0.8242048025131226,
    "G": 0.9839595556259155
  },
  "source_distribution": {
    "G": 7,
    "C": 1,
    "F": 9
  },
  "landmarks": [
    {
      "id": 0,
      "name": "nose",
      "x": 0.49657645904355574,
      "y": 0.13638121386369073,
      "score": 0.9914787411689758,
      "visibility": 0.9914787411689758,
      "source_model": "G"
    },
    {
      "id": 1,
      "name": "left_eye",
      "x": 0.5226236143045956,
      "y": 0.11248701298609376,
      "score": 0.9966848492622375,
      "visibility": 0.9966848492622375,
      "source_model": "C"
    },
    {
      "id": 2,
      "name": "right_eye",
      "x": 0.47714841696951127,
      "y": 0.12019117828458548,
      "score": 0.9965761303901672,
      "visibility": 0.9965761303901672,
      "source_model": "G"
    },
    {
      "id": 3,
      "name": "left_ear",
      "x": 0.540289553710156,
      "y": 0.11857217472667492,
      "score": 0.9924108982086182,
      "visibility": 0.9924108982086182,
      "source_model": "G"
    },
    {
      "id": 4,
      "name": "right_ear",
      "x": 0.4593393784016371,
      "y": 0.1266671925162276,
      "score": 0.9887506365776062,
      "visibility": 0.9887506365776062,
      "source_model": "G"
    },
    {
      "id": 5,
      "name": "left_shoulder",
      "x": 0.5661240816116333,
      "y": 0.21878114342689514,
      "score": 0.9996806383132935,
      "visibility": 0.9996806383132935,
      "source_model": "F"
    },
    {
      "id": 6,
      "name": "right_shoulder",
      "x": 0.383959025144577,
      "y": 0.20080940425395966,
      "score": 0.9996885061264038,
      "visibility": 0.9996885061264038,
      "source_model": "F"
    },
    {
      "id": 7,
      "name": "left_elbow",
      "x": 0.6005880832672119,
      "y": 0.3537096679210663,
      "score": 0.9752467274665833,
      "visibility": 0.9752467274665833,
      "source_model": "F"
    },
    {
      "id": 8,
      "name": "right_elbow",
      "x": 0.33305710492034746,
      "y": 0.2853295411914587,
      "score": 0.9781374931335449,
      "visibility": 0.9781374931335449,
      "source_model": "G"
    },
    {
      "id": 9,
      "name": "left_wrist",
      "x": 0.6309537500556972,
      "y": 0.494181000161916,
      "score": 0.9638916254043579,
      "visibility": 0.9638916254043579,
      "source_model": "G"
    },
    {
      "id": 10,
      "name": "right_wrist",
      "x": 0.3913412311424811,
      "y": 0.3225666230234008,
      "score": 0.9687268733978271,
      "visibility": 0.9687268733978271,
      "source_model": "G"
    },
    {
      "id": 11,
      "name": "left_hip",
      "x": 0.5230951309204102,
      "y": 0.44204553961753845,
      "score": 0.9992805123329163,
      "visibility": 0.9992805123329163,
      "source_model": "F"
    },
    {
      "id": 12,
      "name": "right_hip",
      "x": 0.41873759031295776,
      "y": 0.44000378251075745,
      "score": 0.9993289709091187,
      "visibility": 0.9993289709091187,
      "source_model": "F"
    },
    {
      "id": 13,
      "name": "left_knee",
      "x": 0.5645106434822083,
      "y": 0.6523377299308777,
      "score": 0.9991686344146729,
      "visibility": 0.9991686344146729,
      "source_model": "F"
    },
    {
      "id": 14,
      "name": "right_knee",
      "x": 0.4451048970222473,
      "y": 0.6548207998275757,
      "score": 0.9995050430297852,
      "visibility": 0.9995050430297852,
      "source_model": "F"
    },
    {
      "id": 15,
      "name": "left_ankle",
      "x": 0.601634681224823,
      "y": 0.8855684399604797,
      "score": 0.9989080429077148,
      "visibility": 0.9989080429077148,
      "source_model": "F"
    },
    {
      "id": 16,
      "name": "right_ankle",
      "x": 0.4580443501472473,
      "y": 0.8772934675216675,
      "score": 0.9995296001434326,
      "visibility": 0.9995296001434326,
      "source_model": "F"
    }
  ]
}